<?xml version="1.0" encoding="UTF-8"?>
<objects serializationModel="Studio.02.01.00">
	<object class="AudioFile" id="{b59ea2b4-ba71-4432-be75-5c5a1c17a766}">
		<property name="assetPath">
			<value>turret3.wav</value>
		</property>
		<property name="frequencyInKHz">
			<value>96</value>
		</property>
		<property name="channelCount">
			<value>2</value>
		</property>
		<property name="length">
			<value>1.2822604166666667</value>
		</property>
		<relationship name="masterAssetFolder">
			<destination>{23be83fc-6260-40a7-9288-5325ec9701b6}</destination>
		</relationship>
	</object>
</objects>
